README.txt
setup.py
twitter_filter/__init__.py
twitter_filter/batcher.py
twitter_filter/dates_handler.py
twitter_filter/exceptions_wrapper.py
twitter_filter/file_util.py
twitter_filter/twitter_api.py
twitter_filter/twitter_filter.py
twitter_filter/twitter_listener.py
twitter_filter.egg-info/PKG-INFO
twitter_filter.egg-info/SOURCES.txt
twitter_filter.egg-info/dependency_links.txt
twitter_filter.egg-info/top_level.txt