Metadata-Version: 1.0
Name: twitter-filter
Version: 0.1.dev0
Summary: Twitter Live Data Collector
Home-page: https://github.com/abdulrahimGhazal/twitter_filter
Author: AbdulrahimGhazal
Author-email: abdulrahim.ghazal.1994@gmail.com
License: MIT
Platform: UNKNOWN
